blazeinfer/__init__.py
blazeinfer/generate.py
blazeinfer/main.py
blazeinfer/executor/__init__.py
blazeinfer/executor/model_executor.py
blazeinfer/kernels/__init__.py
blazeinfer/models/__init__.py
blazeinfer/utils/__init__.py
blazeinfer-0.0.2.dist-info/licenses/LICENSE
blazeinfer-0.0.2.dist-info/METADATA
blazeinfer-0.0.2.dist-info/WHEEL
blazeinfer-0.0.2.dist-info/entry_points.txt
blazeinfer-0.0.2.dist-info/top_level.txt
blazeinfer-0.0.2.dist-info/RECORD
